adafruit_binascii.py
adafruit_circuitpython_binascii-2.0.8.dist-info/licenses/LICENSE
adafruit_circuitpython_binascii-2.0.8.dist-info/METADATA
adafruit_circuitpython_binascii-2.0.8.dist-info/WHEEL
adafruit_circuitpython_binascii-2.0.8.dist-info/top_level.txt
adafruit_circuitpython_binascii-2.0.8.dist-info/RECORD
