Metadata-Version: 2.4
Name: adafruit-circuitpython-binascii
Version: 2.0.8
Summary: Helpers for conversions between binary and ASCII
Author-email: Adafruit Industries <circuitpython@adafruit.com>
License: MIT
Project-URL: Homepage, https://github.com/adafruit/Adafruit_CircuitPython_binascii
Keywords: adafruit,blinka,circuitpython,micropython,binascii,binary,,ascii,,conversion
Classifier: Intended Audience :: Developers
Classifier: Topic :: Software Development :: Libraries
Classifier: Topic :: Software Development :: Embedded Systems
Classifier: Topic :: System :: Hardware
Classifier: License :: OSI Approved :: MIT License
Classifier: Programming Language :: Python :: 3
License-File: LICENSE
Requires-Dist: Adafruit-Blinka>=7.2.3
Provides-Extra: optional
Dynamic: license-file
